[
  {
    "from": "1",
    "to": "mix",
    "date": "1385849659158",
    "type": "mail",
    "read": false,
    "replied": false,
    "title": "hello world",
    "content": "nice world here",
    "_id": "52a13d2d2aa9d35f24000001"
  },
  {
    "from": "23",
    "date": "1386322278597",
    "type": "test-result",
    "read": "false",
    "replied": "false",
    "title": "Result: Ist%20ein%20prozessorientiertes%20Layout%20f%C3%BCr%20alle%20Betroffenen%20gleicherma%C3%9Fen%20gut%3F",
    "content": {
      "correct": "true",
      "question": "Ist%20ein%20prozessorientiertes%20Layout%20f%C3%BCr%20alle%20Betroffenen%20gleicherma%C3%9Fen%20gut%3F",
      "answ": [
        {
          "id": "answ38",
          "answ": "Ja",
          "questiontype": "mc"
        },
        {
          "id": "answ55",
          "answ": "Nein",
          "questiontype": "mc"
        }
      ],
      "res": "Nein",
      "videoid": "302"
    },
    "_id": "52a199732aa9d35f240000a7"
  },
  {
    "from": "23",
    "date": "1386322433155",
    "type": "test-result",
    "read": "false",
    "replied": "false",
    "title": "Result: Ist%20ein%20prozessorientiertes%20Layout%20f%C3%BCr%20alle%20Betroffenen%20gleicherma%C3%9Fen%20gut%3F",
    "content": {
      "correct": "true",
      "question": "Ist%20ein%20prozessorientiertes%20Layout%20f%C3%BCr%20alle%20Betroffenen%20gleicherma%C3%9Fen%20gut%3F",
      "answ": [
        {
          "id": "answ38",
          "answ": "Ja",
          "questiontype": "mc"
        },
        {
          "id": "answ55",
          "answ": "Nein",
          "questiontype": "mc"
        }
      ],
      "res": "Nein",
      "videoid": "302"
    },
    "_id": "52a19a0d2aa9d35f240000a8"
  },
  {
    "from": "19",
    "date": "1386343102772",
    "type": "test-result",
    "read": "false",
    "replied": "false",
    "title": "Result: Auf%20welches%20Hilfsmittel%20greift%20man%20bei%20der%20Layout%20Planung%20zur%C3%BCck%2C%20um%20die%20Beziehungen%20zwischen%20den%20einzelnen%20Produktionseinheiten%20aufzuzeigen%3F",
    "content": {
      "question": "Auf%20welches%20Hilfsmittel%20greift%20man%20bei%20der%20Layout%20Planung%20zur%C3%BCck%2C%20um%20die%20Beziehungen%20zwischen%20den%20einzelnen%20Produktionseinheiten%20aufzuzeigen%3F",
      "answ": [
        {
          "id": "answ23",
          "answ": "Homart-Activity-Relationship Diagram",
          "questiontype": "fill-in"
        }
      ],
      "res": "",
      "videoid": "206"
    },
    "_id": "52a1ead05fd21b5c2b000071"
  },
  {
    "from": "67",
    "date": "1386440288662",
    "type": "test-result",
    "read": "false",
    "replied": "false",
    "title": "Result: hello",
    "content": {
      "correct": "true",
      "question": "hello",
      "answ": [
        {
          "id": "answ94",
          "answ": "sd",
          "questiontype": "mc"
        }
      ],
      "res": "sd",
      "videoid": "301"
    },
    "_id": "52a366755fd21b5c2b000072"
  },
  {
    "from": "82",
    "date": "1386505612325",
    "type": "test-result",
    "read": "false",
    "replied": "false",
    "title": "Result: Eine%20Frage",
    "content": {
      "correct": "false",
      "question": "Eine%20Frage",
      "answ": [
        {
          "id": "answ78",
          "answ": "Antwort a",
          "questiontype": "mc"
        },
        {
          "id": "answ32",
          "answ": "Antwort b",
          "questiontype": "mc"
        },
        {
          "id": "answ43",
          "answ": "Antwort c",
          "questiontype": "mc"
        }
      ],
      "res": "Antwort%20b",
      "videoid": "401"
    },
    "_id": "52a465b262ed39404d000071"
  },
  {
    "from": "82",
    "to": "82",
    "date": "",
    "replyto": "52a465b262ed39404d000071",
    "type": "feedback",
    "read": "false",
    "replied": "false",
    "title": "Result: ",
    "content": "gut",
    "_id": "52a465bb62ed39404d000072"
  },
  {
    "from": "23",
    "date": "1386615557088",
    "type": "test-result",
    "read": "false",
    "replied": "false",
    "title": "Result: Ist%20ein%20prozessorientiertes%20Layout%20f%C3%BCr%20alle%20Betroffenen%20gleicherma%C3%9Fen%20gut%3F",
    "content": {
      "correct": "true",
      "question": "Ist%20ein%20prozessorientiertes%20Layout%20f%C3%BCr%20alle%20Betroffenen%20gleicherma%C3%9Fen%20gut%3F",
      "answ": [
        {
          "id": "answ38",
          "answ": "Ja",
          "questiontype": "mc"
        },
        {
          "id": "answ55",
          "answ": "Nein",
          "questiontype": "mc"
        }
      ],
      "res": "Nein",
      "videoid": "302"
    },
    "_id": "52a6133962ed39404d000073"
  },
  {
    "from": "23",
    "date": "1386615787588",
    "type": "test-result",
    "read": "false",
    "replied": "false",
    "title": "Result: Ist%20ein%20prozessorientiertes%20Layout%20f%C3%BCr%20alle%20Betroffenen%20gleicherma%C3%9Fen%20gut%3F",
    "content": {
      "correct": "true",
      "question": "Ist%20ein%20prozessorientiertes%20Layout%20f%C3%BCr%20alle%20Betroffenen%20gleicherma%C3%9Fen%20gut%3F",
      "answ": [
        {
          "id": "answ49",
          "answ": "Ja",
          "questiontype": "mc"
        },
        {
          "id": "answ43",
          "answ": "Nein",
          "questiontype": "mc"
        }
      ],
      "res": "Nein",
      "videoid": "302"
    },
    "_id": "52a6142062ed39404d000074"
  },
  {
    "from": "23",
    "date": "1386615830312",
    "type": "test-result",
    "read": "false",
    "replied": "false",
    "title": "Result: Ist%20ein%20prozessorientiertes%20Layout%20f%C3%BCr%20alle%20Betroffenen%20gleicherma%C3%9Fen%20gut%3F",
    "content": {
      "correct": "true",
      "question": "Ist%20ein%20prozessorientiertes%20Layout%20f%C3%BCr%20alle%20Betroffenen%20gleicherma%C3%9Fen%20gut%3F",
      "answ": [
        {
          "id": "answ49",
          "answ": "Ja",
          "questiontype": "mc"
        },
        {
          "id": "answ43",
          "answ": "Nein",
          "questiontype": "mc"
        }
      ],
      "res": "Nein",
      "videoid": "302"
    },
    "_id": "52a6144a62ed39404d000075"
  },
  {
    "from": "23",
    "date": "1386616280296",
    "type": "test-result",
    "read": "false",
    "replied": "false",
    "title": "Result: Von%20wie%20vielen%20Kostenfaktoren%20ist%20das%20Modell%20abh%C3%A4ngig%3F",
    "content": {
      "correct": "true",
      "question": "Von%20wie%20vielen%20Kostenfaktoren%20ist%20das%20Modell%20abh%C3%A4ngig%3F",
      "answ": [
        {
          "id": "answ49",
          "answ": "1",
          "questiontype": "mc"
        },
        {
          "id": "answ43",
          "answ": "2",
          "questiontype": "mc"
        },
        {
          "id": "answ66",
          "answ": "3",
          "questiontype": "mc"
        }
      ],
      "res": "2",
      "videoid": "302"
    },
    "_id": "52a6160c62ed39404d000076"
  },
  {
    "from": "23",
    "date": "1386616711506",
    "type": "test-result",
    "read": "false",
    "replied": "false",
    "title": "Result: Von%20wie%20vielen%20Kostenfaktoren%20ist%20das%20Modell%20abh%C3%A4ngig%3F",
    "content": {
      "correct": "true",
      "question": "Von%20wie%20vielen%20Kostenfaktoren%20ist%20das%20Modell%20abh%C3%A4ngig%3F",
      "answ": [
        {
          "id": "answ49",
          "answ": "1",
          "questiontype": "mc"
        },
        {
          "id": "answ43",
          "answ": "2",
          "questiontype": "mc"
        },
        {
          "id": "answ66",
          "answ": "3",
          "questiontype": "mc"
        }
      ],
      "res": "2",
      "videoid": "302"
    },
    "_id": "52a617bc62ed39404d000077"
  },
  {
    "from": "23",
    "date": "1386616797385",
    "type": "test-result",
    "read": "false",
    "replied": "false",
    "title": "Result: Kann%20eine%20Abteilung%20in%20der%20MAtrix%20eine%20Beziehung%20zu%20sich%20selber%20haben%3F",
    "content": {
      "correct": "true",
      "question": "Kann%20eine%20Abteilung%20in%20der%20MAtrix%20eine%20Beziehung%20zu%20sich%20selber%20haben%3F",
      "answ": [
        {
          "id": "answ49",
          "answ": "Ja",
          "questiontype": "mc"
        },
        {
          "id": "answ43",
          "answ": "Nein",
          "questiontype": "mc"
        }
      ],
      "res": "Nein",
      "videoid": "302"
    },
    "_id": "52a6181262ed39404d000078"
  },
  {
    "from": "23",
    "date": "1386616835948",
    "type": "test-result",
    "read": "false",
    "replied": "false",
    "title": "Result: Wie%20wird%20die%20Matrix%20genannt%3F",
    "content": {
      "correct": "true",
      "question": "Wie%20wird%20die%20Matrix%20genannt%3F",
      "answ": [
        {
          "id": "answ11",
          "answ": "Kostenmatrix",
          "questiontype": "mc"
        },
        {
          "id": "answ100",
          "answ": "Zeitmatrix",
          "questiontype": "mc"
        },
        {
          "id": "answ14",
          "answ": "Qualitätsmatrix",
          "questiontype": "mc"
        }
      ],
      "res": "Kostenmatrix",
      "videoid": "302"
    },
    "_id": "52a6183862ed39404d000079"
  },
  {
    "from": "9",
    "date": "1386663836274",
    "type": "test-result",
    "read": "false",
    "replied": "false",
    "title": "Result: Was%20sind%20die%20typischen%20Ziele%20im%20Anlagenlayout%3F",
    "content": {
      "correct": "true",
      "question": "Was%20sind%20die%20typischen%20Ziele%20im%20Anlagenlayout%3F",
      "answ": [
        {
          "id": "answ20",
          "answ": "huhu",
          "questiontype": "mc"
        },
        {
          "id": "answ30",
          "answ": "csd",
          "questiontype": "mc"
        }
      ],
      "res": "csd",
      "videoid": "9"
    },
    "_id": "52a6cfd462ed39404d00007a"
  },
  {
    "from": "9",
    "to": "9",
    "date": "",
    "replyto": "52a6cfd462ed39404d00007a",
    "type": "feedback",
    "read": "false",
    "replied": "false",
    "title": "Result: ",
    "content": "",
    "_id": "52a6d39762ed39404d00007b"
  },
  {
    "from": "9",
    "date": "1386665899074",
    "type": "test-result",
    "read": "false",
    "replied": "false",
    "title": "Result: Was%20sind%20die%20Merkmale%20eines%20Produkt-Layouts%3F",
    "content": {
      "correct": "true",
      "question": "Was%20sind%20die%20Merkmale%20eines%20Produkt-Layouts%3F",
      "answ": [
        {
          "id": "answ66",
          "answ": "glatte und logische Stromlinien",
          "questiontype": "mc"
        },
        {
          "id": "answ53",
          "answ": "geringe Lagerbestände",
          "questiontype": "mc"
        },
        {
          "id": "answ97",
          "answ": "geringe Gesamtproduktionszeit",
          "questiontype": "mc"
        },
        {
          "id": "answ74",
          "answ": "reduziertes Materialhandling",
          "questiontype": "mc"
        },
        {
          "id": "answ73",
          "answ": "leicht ausführbare Tätigkeiten",
          "questiontype": "mc"
        },
        {
          "id": "answ88",
          "answ": "einfache Produktionsplanung und Kontrolle",
          "questiontype": "mc"
        },
        {
          "id": "answ80",
          "answ": "reduzierung von Transport- und Lagerflächen",
          "questiontype": "mc"
        }
      ],
      "res": "glatte%20und%20logische%20Stromlinien%2Cgeringe%20Lagerbest%C3%A4nde%2Cgeringe%20Gesamtproduktionszeit%2Creduziertes%20Materialhandling%2Cleicht%20ausf%C3%BChrbare%20T%C3%A4tigkeiten%2Ceinfache%20Produktionsplanung%20und%20Kontrolle%2Creduzierung%20von%20Transport-%20und%20Lagerfl%C3%A4chen",
      "videoid": "9"
    },
    "_id": "52a6d7e362ed39404d00007c"
  },
  {
    "from": "9",
    "date": "1386666287293",
    "type": "test-result",
    "read": "false",
    "replied": "false",
    "title": "Result: Was%20sind%20die%20Merkmale%20eines%20Prozess-Layouts%3F",
    "content": {
      "correct": "true",
      "question": "Was%20sind%20die%20Merkmale%20eines%20Prozess-Layouts%3F",
      "answ": [
        {
          "id": "answ66",
          "answ": "bessere Auslastung von Maschinen",
          "questiontype": "mc"
        },
        {
          "id": "answ2",
          "answ": "hohes Maß an flexibilität",
          "questiontype": "mc"
        },
        {
          "id": "answ22",
          "answ": "verhältnismäßig geringes Anlagenkapital",
          "questiontype": "mc"
        },
        {
          "id": "answ71",
          "answ": "mehr Zufriedenheit am Arbeitsplatz",
          "questiontype": "mc"
        },
        {
          "id": "answ42",
          "answ": "fachaufsicht ist möglich",
          "questiontype": "mc"
        }
      ],
      "res": "bessere%20Auslastung%20von%20Maschinen%2Chohes%20Ma%C3%9F%20an%20flexibilit%C3%A4t%2Cverh%C3%A4ltnism%C3%A4%C3%9Fig%20geringes%20Anlagenkapital%2Cmehr%20Zufriedenheit%20am%20Arbeitsplatz%2Cfachaufsicht%20ist%20m%C3%B6glich",
      "videoid": "9"
    },
    "_id": "52a6d96862ed39404d00007d"
  },
  {
    "from": "23",
    "date": "1386667843689",
    "type": "test-result",
    "read": "false",
    "replied": "false",
    "title": "Result: Was%20muss%20bei%20einem%20arbeitszellenbasierenden%20LAyout%20arrangiert%20werden%3F",
    "content": {
      "question": "Was%20muss%20bei%20einem%20arbeitszellenbasierenden%20LAyout%20arrangiert%20werden%3F",
      "answ": [
        {
          "id": "answ14",
          "answ": "Meunsch und Maschienen",
          "questiontype": "fill-in"
        }
      ],
      "res": "Mensch%20und%20Maschienen",
      "videoid": "301"
    },
    "_id": "52a6df7e62ed39404d00007e"
  },
  {
    "from": "23",
    "date": "1386669201878",
    "type": "test-result",
    "read": "false",
    "replied": "false",
    "title": "Result: Mit%20welchen%20Faktoren%20wird%20die%20Anzahl%20der%20Arbeiter%20bestimmt%3F",
    "content": {
      "correct": "true",
      "question": "Mit%20welchen%20Faktoren%20wird%20die%20Anzahl%20der%20Arbeiter%20bestimmt%3F",
      "answ": [
        {
          "id": "answ31",
          "answ": "Stillstandszeit",
          "questiontype": "mc"
        },
        {
          "id": "answ62",
          "answ": "Gesamte Arbeitszeit",
          "questiontype": "mc"
        },
        {
          "id": "answ1",
          "answ": "Taktzeit",
          "questiontype": "mc"
        },
        {
          "id": "answ9",
          "answ": "Anlieferzeit",
          "questiontype": "mc"
        }
      ],
      "res": "Gesamte%20Arbeitszeit%2CTaktzeit",
      "videoid": "301"
    },
    "_id": "52a6e4cc62ed39404d00007f"
  },
  {
    "from": "44",
    "date": "1386672755700",
    "type": "test-result",
    "read": "false",
    "replied": "false",
    "title": "Result: Was%20sind%20die%20Bedingungen%20f%C3%BCr%20einen%20Euler-Graphen%3F",
    "content": {
      "question": "Was%20sind%20die%20Bedingungen%20f%C3%BCr%20einen%20Euler-Graphen%3F",
      "answ": [
        {
          "id": "answ16",
          "answ": "Was sind die Bedingungen für einen Euler-Graphen?",
          "questiontype": "fill-in"
        }
      ],
      "res": "",
      "videoid": "7"
    },
    "_id": "52a6f2b062ed39404d000080"
  },
  {
    "from": "44",
    "date": "1386672765000",
    "type": "test-result",
    "read": "false",
    "replied": "false",
    "title": "Result: Was%20sind%20die%20Bedingungen%20f%C3%BCr%20einen%20Euler-Graphen%3F",
    "content": {
      "question": "Was%20sind%20die%20Bedingungen%20f%C3%BCr%20einen%20Euler-Graphen%3F",
      "answ": [
        {
          "id": "answ16",
          "answ": "Was sind die Bedingungen für einen Euler-Graphen?",
          "questiontype": "fill-in"
        }
      ],
      "res": "",
      "videoid": "7"
    },
    "_id": "52a6f2ba62ed39404d000081"
  },
  {
    "from": "34",
    "to": "34",
    "date": "",
    "replyto": "52a8c9da866688e85f000075",
    "type": "feedback",
    "read": "false",
    "replied": "false",
    "title": "Result: ",
    "content": "",
    "_id": "52a8e292866688e85f000077"
  },
  {
    "from": "44",
    "date": "1386673133906",
    "type": "test-result",
    "read": "false",
    "replied": "false",
    "title": "Result: Was%20ist%20die%20Bedingung%20des%20Chines%20Postman%20Problems%3F",
    "content": {
      "question": "Was%20ist%20die%20Bedingung%20des%20Chines%20Postman%20Problems%3F",
      "answ": [
        {
          "id": "answ72",
          "answ": "Was ist die Bedingung des Chines Postman Problems?",
          "questiontype": "fill-in"
        }
      ],
      "res": "",
      "videoid": "7"
    },
    "_id": "52a6f42b62ed39404d000082"
  },
  {
    "from": "61",
    "date": "1386703911997",
    "type": "test-result",
    "read": "false",
    "replied": "false",
    "title": "Result: In%20welchen%20F%C3%A4llen%20kann%20das%20Chinese%20Postman%20Problem%20seine%20Anwendung%20finden%3F",
    "content": {
      "question": "In%20welchen%20F%C3%A4llen%20kann%20das%20Chinese%20Postman%20Problem%20seine%20Anwendung%20finden%3F",
      "answ": [
        {
          "id": "answ56",
          "answ": "Briefzustellung, Strassenreinigung, Müllabfuhr",
          "questiontype": "fill-in"
        }
      ],
      "res": "M%C3%BCllentsorgung%2C%20Leerung%20des%20Briefkastens",
      "videoid": "201"
    },
    "_id": "52a76a5f62ed39404d000083"
  },
  {
    "from": "61",
    "date": "1386704738767",
    "type": "test-result",
    "read": "false",
    "replied": "false",
    "title": "Result: Warum%20ist%20der%20Graph%20Euler%20geworden%3F",
    "content": {
      "question": "Warum%20ist%20der%20Graph%20Euler%20geworden%3F",
      "answ": [
        {
          "id": "answ64",
          "answ": "Weil jeder Knoten einen geraden Knotengrad geworgen hat ",
          "questiontype": "fill-in"
        }
      ],
      "res": "",
      "videoid": "201"
    },
    "_id": "52a76d9a62ed39404d000084"
  },
  {
    "from": "61",
    "date": "1386705097787",
    "type": "test-result",
    "read": "false",
    "replied": "false",
    "title": "Result: Warum%20ist%20der%20Graph%20Euler%20geworden%3F",
    "content": {
      "question": "Warum%20ist%20der%20Graph%20Euler%20geworden%3F",
      "answ": [
        {
          "id": "answ64",
          "answ": "Weil jeder Knoten einen geraden Knotengrad geworgen hat ",
          "questiontype": "fill-in"
        }
      ],
      "res": "",
      "videoid": "207"
    },
    "_id": "52a76f0162ed39404d000085"
  },
  {
    "from": "61",
    "date": "1386705134879",
    "type": "test-result",
    "read": "false",
    "replied": "false",
    "title": "Result: Warum%20ist%20der%20Graph%20Euler%20geworden%3F",
    "content": {
      "question": "Warum%20ist%20der%20Graph%20Euler%20geworden%3F",
      "answ": [
        {
          "id": "answ64",
          "answ": "Weil jeder Knoten einen geraden Knotengrad geworgen hat ",
          "questiontype": "fill-in"
        }
      ],
      "res": "",
      "videoid": "207"
    },
    "_id": "52a76f2662ed39404d000086"
  },
  {
    "from": "61",
    "date": "1386707751634",
    "type": "test-result",
    "read": "false",
    "replied": "false",
    "title": "Result: Wie%20viel%20Kanten%20muss%20man%20verdoppeln%2C%20um%20die%20minimale%20gesamte%20Entfernung%20265%20km%20zu%20erreichen%3F",
    "content": {
      "correct": "true",
      "question": "Wie%20viel%20Kanten%20muss%20man%20verdoppeln%2C%20um%20die%20minimale%20gesamte%20Entfernung%20265%20km%20zu%20erreichen%3F",
      "answ": [
        {
          "id": "answ59",
          "answ": "3",
          "questiontype": "mc"
        }
      ],
      "res": "3",
      "videoid": "201"
    },
    "_id": "52a7795f62ed39404d000087"
  },
  {
    "from": "61",
    "date": "1386709769494",
    "type": "test-result",
    "read": "false",
    "replied": "false",
    "title": "Result: Wie%20viel%20Kanten%20muss%20man%20verdoppeln%2C%20um%20die%20minimale%20gesamte%20Entfernung%20265%20km%20zu%20erreichen%3F",
    "content": {
      "correct": "true",
      "question": "Wie%20viel%20Kanten%20muss%20man%20verdoppeln%2C%20um%20die%20minimale%20gesamte%20Entfernung%20265%20km%20zu%20erreichen%3F",
      "answ": [
        {
          "id": "answ51",
          "answ": "1",
          "questiontype": "mc"
        },
        {
          "id": "answ49",
          "answ": "2",
          "questiontype": "mc"
        },
        {
          "id": "answ55",
          "answ": "3",
          "questiontype": "mc"
        },
        {
          "id": "answ19",
          "answ": "6",
          "questiontype": "mc"
        }
      ],
      "res": "3",
      "videoid": "207"
    },
    "_id": "52a7814162ed39404d000088"
  },
  {
    "from": "61",
    "date": "1386709985266",
    "type": "test-result",
    "read": "false",
    "replied": "false",
    "title": "Result: Wie%20viel%20Kanten%20muss%20man%20verdoppeln%2C%20um%20die%20minimale%20gesamte%20Entfernung%20265%20km%20zu%20erreichen%3F",
    "content": {
      "correct": "true",
      "question": "Wie%20viel%20Kanten%20muss%20man%20verdoppeln%2C%20um%20die%20minimale%20gesamte%20Entfernung%20265%20km%20zu%20erreichen%3F",
      "answ": [
        {
          "id": "answ86",
          "answ": "1",
          "questiontype": "mc"
        },
        {
          "id": "answ44",
          "answ": "2",
          "questiontype": "mc"
        },
        {
          "id": "answ51",
          "answ": "3",
          "questiontype": "mc"
        },
        {
          "id": "answ15",
          "answ": "6",
          "questiontype": "mc"
        }
      ],
      "res": "3",
      "videoid": "207"
    },
    "_id": "52a7821962ed39404d000089"
  },
  {
    "from": "44",
    "date": "1386750678018",
    "type": "test-result",
    "read": "false",
    "replied": "false",
    "title": "Result: Welche%20Probleme%20k%C3%B6nnen%20mit%20den%20Fahrzeugen%20auftreten%3F",
    "content": {
      "correct": "true",
      "question": "Welche%20Probleme%20k%C3%B6nnen%20mit%20den%20Fahrzeugen%20auftreten%3F",
      "answ": [
        {
          "id": "answ77",
          "answ": "Beschränkte Kapazität",
          "questiontype": "mc"
        },
        {
          "id": "answ41",
          "answ": "Es sollen alle Fahrzeuge genutzt werden",
          "questiontype": "mc"
        },
        {
          "id": "answ3",
          "answ": "Es sollen so wenig Fahrzeuge wie möglich genzutzt werden",
          "questiontype": "mc"
        }
      ],
      "res": "Beschr%C3%A4nkte%20Kapazit%C3%A4t%2CEs%20sollen%20alle%20Fahrzeuge%20genutzt%20werden%2CEs%20sollen%20so%20wenig%20Fahrzeuge%20wie%20m%C3%B6glich%20genzutzt%20werden",
      "videoid": "7"
    },
    "_id": "52a8231d866688e85f000071"
  },
  {
    "from": "45",
    "date": "1386785024966",
    "type": "test-result",
    "read": "false",
    "replied": "false",
    "title": "Result: Wie%20viel%20Methoden%20werden%20in%20Pr%C3%A4sentation%20behandelt%3F",
    "content": {
      "correct": "true",
      "question": "Wie%20viel%20Methoden%20werden%20in%20Pr%C3%A4sentation%20behandelt%3F",
      "answ": [
        {
          "id": "answ50",
          "answ": "5",
          "questiontype": "mc"
        },
        {
          "id": "answ74",
          "answ": "4",
          "questiontype": "mc"
        },
        {
          "id": "answ81",
          "answ": "3",
          "questiontype": "mc"
        }
      ],
      "res": "4",
      "videoid": "4"
    },
    "_id": "52a8a94c866688e85f000072"
  },
  {
    "from": "68",
    "date": "1386785478266",
    "type": "test-result",
    "read": "false",
    "replied": "false",
    "title": "Result: Womit%20sollte%20man%20bei%20der%20Arbeitsprduktivit%C3%A4t%20rechnen%3F",
    "content": {
      "question": "Womit%20sollte%20man%20bei%20der%20Arbeitsprduktivit%C3%A4t%20rechnen%3F",
      "answ": [
        {
          "id": "answ90",
          "answ": "- Gehälter sind nicht die einzig richtigen Kosten,\n- niedrigere Arbeitsprduktivität kann die gesamten Kosten erhöhen ",
          "questiontype": "fill-in"
        }
      ],
      "res": "",
      "videoid": "301"
    },
    "_id": "52a8ab2a866688e85f000073"
  },
  {
    "from": "68",
    "date": "1386787871367",
    "type": "test-result",
    "read": "false",
    "replied": "false",
    "title": "Result: Welche%20Planungszeitr%C3%A4ume%20f%C3%BCr%20Kapazit%C3%A4t%20sind%20m%C3%B6glich%3F",
    "content": {
      "correct": "true",
      "question": "Welche%20Planungszeitr%C3%A4ume%20f%C3%BCr%20Kapazit%C3%A4t%20sind%20m%C3%B6glich%3F",
      "answ": [
        {
          "id": "answ55",
          "answ": "Langgfristig, Mittelfristig, Operativ",
          "questiontype": "mc"
        },
        {
          "id": "answ27",
          "answ": "Langfristig",
          "questiontype": "mc"
        },
        {
          "id": "answ98",
          "answ": "Mittelfristig",
          "questiontype": "mc"
        },
        {
          "id": "answ32",
          "answ": "Operativ",
          "questiontype": "mc"
        }
      ],
      "res": "Langgfristig%2C%20Mittelfristig%2C%20Operativ",
      "videoid": "304"
    },
    "_id": "52a8b484866688e85f000074"
  },
  {
    "from": "34",
    "date": "1386793360062",
    "type": "test-result",
    "read": "false",
    "replied": "false",
    "title": "Result: Was%20versteht%20man%20unter%20dem%20Begriff%20%22Betriebliche%20Optimierung%22%3F",
    "content": {
      "question": "Was%20versteht%20man%20unter%20dem%20Begriff%20%22Betriebliche%20Optimierung%22%3F",
      "answ": [
        {
          "id": "answ94",
          "answ": "Betriebliche Optimierung oder Optimierung der logistischen Leistung beinhaltet Just-in-time Planung, Minimierung der Lager- und Transportkosten, schnellmöglichste Erfüllung der Kundenaufträge.",
          "questiontype": "fill-in"
        }
      ],
      "res": "",
      "videoid": "5"
    },
    "_id": "52a8c9da866688e85f000075"
  },
  {
    "from": "34",
    "date": "1386793683666",
    "type": "test-result",
    "read": "false",
    "replied": "false",
    "title": "Result: Was%20kann%20durch%20WMS%20optimiert%20werden%3F",
    "content": {
      "question": "Was%20kann%20durch%20WMS%20optimiert%20werden%3F",
      "answ": [
        {
          "id": "answ94",
          "answ": "Betriebliche Optimierung oder Optimierung der logistischen Leistung beinhaltet Just-in-time Planung, Minimierung der Lager- und Transportkosten, schnellmöglichste Erfüllung der Kundenaufträge.",
          "questiontype": "fill-in"
        }
      ],
      "res": "",
      "videoid": "5"
    },
    "_id": "52a8cb1e866688e85f000076"
  },
  {
    "from": "34",
    "date": "1386800244892",
    "type": "test-result",
    "read": "false",
    "replied": "false",
    "title": "Result: Was%20versteht%20man%20unter%20dem%20Begriff%20%22Betriebliche%20Optimierung%22%3F",
    "content": {
      "question": "Was%20versteht%20man%20unter%20dem%20Begriff%20%22Betriebliche%20Optimierung%22%3F",
      "answ": [
        {
          "id": "answ94",
          "answ": "Betriebliche Optimierung oder Optimierung der logistischen Leistung beinhaltet Just-in-time Planung, Minimierung der Lager- und Transportkosten, schnellmöglichste Erfüllung der Kundenaufträge.",
          "questiontype": "fill-in"
        }
      ],
      "res": "",
      "videoid": "5"
    },
    "_id": "52a8e4c0866688e85f000078"
  },
  {
    "from": "34",
    "to": "34",
    "date": "",
    "replyto": "52a8cb1e866688e85f000076",
    "type": "feedback",
    "read": "false",
    "replied": "false",
    "title": "Result: ",
    "content": "",
    "_id": "52a8e4d8866688e85f000079"
  },
  {
    "from": "61",
    "date": "1386826346642",
    "type": "test-result",
    "read": "false",
    "replied": "false",
    "title": "Result: Warum%20ist%20der%20Graph%20Euler%20geworden%3F",
    "content": {
      "question": "Warum%20ist%20der%20Graph%20Euler%20geworden%3F",
      "answ": [
        {
          "id": "answ57",
          "answ": "Weil jeder Knoten einen geraden Knotengrad erworben hat.",
          "questiontype": "fill-in"
        }
      ],
      "res": "",
      "videoid": "207"
    },
    "_id": "52a948b1866688e85f00007a"
  },
  {
    "from": "82",
    "date": "1386929098524",
    "type": "test-result",
    "read": "false",
    "replied": "false",
    "title": "Result: Eine%20Frage",
    "content": {
      "correct": "false",
      "question": "Eine%20Frage",
      "answ": [
        {
          "id": "answ78",
          "answ": "Antwort a",
          "questiontype": "mc"
        },
        {
          "id": "answ32",
          "answ": "Antwort b",
          "questiontype": "mc"
        },
        {
          "id": "answ43",
          "answ": "Antwort c",
          "questiontype": "mc"
        }
      ],
      "res": "Antwort%20b",
      "videoid": "401"
    },
    "_id": "52aadc2a866688e85f00007b"
  },
  {
    "from": "82",
    "to": "82",
    "date": "",
    "replyto": "52a465b262ed39404d000071",
    "type": "feedback",
    "read": "false",
    "replied": "false",
    "title": "Result: ",
    "content": "",
    "_id": "52aadc34866688e85f00007c"
  },
  {
    "from": "82",
    "date": "1386929200063",
    "type": "test-result",
    "read": "false",
    "replied": "false",
    "title": "Result: Noch%20eine%20Frage",
    "content": {
      "correct": "true",
      "question": "Noch%20eine%20Frage",
      "answ": [
        {
          "id": "answ4",
          "answ": "richtig",
          "questiontype": "mc"
        },
        {
          "id": "answ22",
          "answ": "falsch",
          "questiontype": "mc"
        }
      ],
      "res": "richtig",
      "videoid": "401"
    },
    "_id": "52aadc90866688e85f00007d"
  }
]
